LICENSE-MIT
MANIFEST.in
README.rst
rome.py
setup.py
rome.egg-info/PKG-INFO
rome.egg-info/SOURCES.txt
rome.egg-info/dependency_links.txt
rome.egg-info/top_level.txt