Metadata-Version: 1.1
Name: rome
Version: 0.0.1
Summary: A practical Roman numerals implementation
Home-page: http://github.com/halst/rome
Author: Vladimir Keleshev
Author-email: vladimir@keleshev.com
License: MIT
Keywords: roman numerals
Platform: UNKNOWN
Classifier: Development Status :: 3 - Alpha
Classifier: Topic :: Utilities
Classifier: Programming Language :: Python :: 2.7
Classifier: License :: OSI Approved :: MIT License
